pytest_envvars/__init__.py
pytest_envvars/django_utils.py
pytest_envvars-1.2.1.dist-info/LICENSE
pytest_envvars-1.2.1.dist-info/METADATA
pytest_envvars-1.2.1.dist-info/WHEEL
pytest_envvars-1.2.1.dist-info/entry_points.txt
pytest_envvars-1.2.1.dist-info/top_level.txt
pytest_envvars-1.2.1.dist-info/RECORD
