Metadata-Version: 2.1
Name: pytest-envvars
Version: 1.2.1
Summary: Pytest plugin to validate use of envvars on your tests 
Home-page: https://github.com/rafaelhenrique/pytest-envvars
Author: Rafael Henrique da Silva Correia
Author-email: rafael@abraseucodigo.com.br
Maintainer: Rafael Henrique da Silva Correia
Maintainer-email: rafael@abraseucodigo.com.br
License: MIT
Platform: UNKNOWN
Classifier: Development Status :: 5 - Production/Stable
Classifier: Framework :: Pytest
Classifier: Intended Audience :: Developers
Classifier: Topic :: Software Development :: Testing
Classifier: Programming Language :: Python
Classifier: Programming Language :: Python :: 3
Classifier: Programming Language :: Python :: 3.7
Classifier: Programming Language :: Python :: 3.8
Classifier: Programming Language :: Python :: Implementation :: CPython
Classifier: Operating System :: OS Independent
Classifier: License :: OSI Approved :: MIT License
Requires-Dist: pytest (>=3.0.0)
